db4v2x/__init__.py
db4v2x/consts.py
db4v2x/delete.py
db4v2x/get.py
db4v2x/get_remote.py
db4v2x/save.py
db4v2x/utils.py
db4v2x/redis/__init__.py
db4v2x/redis/api/delete.py
db4v2x/redis/api/get.py
db4v2x/redis/api/save.py
db4v2x/redis/client/kvstore.py
db4v2x/redis/client/scripts.py
db4v2x_simple-0.1.0.dist-info/METADATA
db4v2x_simple-0.1.0.dist-info/WHEEL
db4v2x_simple-0.1.0.dist-info/top_level.txt
db4v2x_simple-0.1.0.dist-info/RECORD
