Metadata-Version: 2.4
Name: db4v2x-simple
Version: 0.1.0
Summary: Simple Database Interface for V2X Systems
Author: Xinlong Zhao
License: MIT
Requires-Python: >=3.9
Requires-Dist: aioredis>=2.0
Requires-Dist: orjson
Requires-Dist: paho-mqtt
Requires-Dist: faststruct-simple
